ezboot
