Metadata-Version: 1.0
Name: ezboot
Version: 1.1.2
Summary: Automatically configure a Boot2Gecko Device. It's so ez!
Home-page: https://github.com/kumar303/ezboot
Author: Kumar McMillan
Author-email: kumar.mcmillan@gmail.com
License: Apache 2
Platform: UNKNOWN
